mod_updater/__init__.py
mod_updater/__main__.py
mod_updater/mod_updater.py
mod_updater/parser.py
mod_updater/sources/__init__.py
mod_updater/sources/base.py
mod_updater/sources/github.py
mod_updater/util/__init__.py
mod_updater/util/utils.py
test/__init__.py
test/test_parser.py
test/sources/__init__.py
test/sources/base.py
test/sources/test_github.py
mod_updater-0.2.0.dist-info/LICENSE
mod_updater-0.2.0.dist-info/METADATA
mod_updater-0.2.0.dist-info/WHEEL
mod_updater-0.2.0.dist-info/entry_points.txt
mod_updater-0.2.0.dist-info/top_level.txt
mod_updater-0.2.0.dist-info/RECORD
